finetuning_suite/__init__.py
finetuning_suite/finetuner.py
finetuning_suite/inference/__init__.py
finetuning_suite/inference/base.py
finetuning_suite/inference/gptq.py
finetuning_suite/inference/hf_model.py
finetuning_suite/processing/__init__.py
finetuning_suite/processing/base.py
finetuning_suite/processing/build_dataset.py
finetuning_suite/trainer/__init__.py
finetuning_suite/trainer/base.py
finetuning_suite/utils/__init__.py
finetuning_suite/utils/main.py
finetuning_suite-0.1.6.dist-info/LICENSE
finetuning_suite-0.1.6.dist-info/WHEEL
finetuning_suite-0.1.6.dist-info/METADATA
finetuning_suite-0.1.6.dist-info/RECORD
